weightlogger/__init__.py
weightlogger/app.py
weightlogger/constant.py
weightlogger/controller.py
weightlogger/images/greenarrow.png
weightlogger/images/redarrow.png
wlg_fayefv-0.3.1.dist-info/LICENSE
wlg_fayefv-0.3.1.dist-info/METADATA
wlg_fayefv-0.3.1.dist-info/WHEEL
wlg_fayefv-0.3.1.dist-info/top_level.txt
wlg_fayefv-0.3.1.dist-info/RECORD
